{
  "project_info": {
    "project_number": "780580866573",
    "firebase_url": "https://fingerprint-2938f.firebaseio.com",
    "project_id": "fingerprint-2938f",
    "storage_bucket": "fingerprint-2938f.appspot.com"
  },
  "client": [
    {
      "client_info": {
        "mobilesdk_app_id": "1:780580866573:android:3dfe35d306713d18",
        "android_client_info": {
          "package_name": "info.androidhive.fingerprint"
        }
      },
      "oauth_client": [
        {
          "client_id": "780580866573-niemjvav4am9sfi2dqf2rjlal8tpejmn.apps.googleusercontent.com",
          "client_type": 3
        }
      ],
      "api_key": [
        {
          "current_key": "AIzaSyDC-80-K8mkJI30p8JXiozTUHE34oxiw3I"
        }
      ],
      "services": {
        "analytics_service": {
          "status": 1
        },
        "appinvite_service": {
          "status": 1,
          "other_platform_oauth_client": []
        },
        "ads_service": {
          "status": 2
        }
      }
    }
  ],
  "configuration_version": "1"
}